kuber/__init__.py
kuber/_types.py
kuber/definitions/__init__.py
kuber/definitions/_abstracts.py
kuber/definitions/_support.py
kuber/definitions/_types.py
kuber/execution.py
kuber/interface/__init__.py
kuber/interface/_parsing.py
kuber/kube_api.py
kuber/latest/__init__.py
kuber/latest/admissionregistration_v1.py
kuber/latest/admissionregistration_v1alpha1.py
kuber/latest/admissionregistration_v1beta1.py
kuber/latest/apiextensions_v1.py
kuber/latest/apimachinery_runtime.py
kuber/latest/apimachinery_version.py
kuber/latest/apiregistration_v1.py
kuber/latest/apiserverinternal_v1alpha1.py
kuber/latest/apps_v1.py
kuber/latest/authentication_v1.py
kuber/latest/authorization_v1.py
kuber/latest/autoscaling_v1.py
kuber/latest/autoscaling_v2.py
kuber/latest/batch_v1.py
kuber/latest/certificates_v1.py
kuber/latest/certificates_v1alpha1.py
kuber/latest/certificates_v1beta1.py
kuber/latest/coordination_v1.py
kuber/latest/coordination_v1alpha2.py
kuber/latest/coordination_v1beta1.py
kuber/latest/core_v1.py
kuber/latest/custom_v1.py
kuber/latest/discovery_v1.py
kuber/latest/events_v1.py
kuber/latest/flowcontrol_v1.py
kuber/latest/meta_v1.py
kuber/latest/networking_v1.py
kuber/latest/networking_v1beta1.py
kuber/latest/node_v1.py
kuber/latest/policy_v1.py
kuber/latest/rbac_v1.py
kuber/latest/resource_v1alpha3.py
kuber/latest/resource_v1beta1.py
kuber/latest/resource_v1beta2.py
kuber/latest/scheduling_v1.py
kuber/latest/storage_v1.py
kuber/latest/storage_v1alpha1.py
kuber/latest/storage_v1beta1.py
kuber/latest/storagemigration_v1alpha1.py
kuber/management/__init__.py
kuber/management/arrays.py
kuber/management/configuration.py
kuber/management/creation.py
kuber/pre/__init__.py
kuber/pre/admissionregistration_v1.py
kuber/pre/admissionregistration_v1alpha1.py
kuber/pre/admissionregistration_v1beta1.py
kuber/pre/apiextensions_v1.py
kuber/pre/apimachinery_runtime.py
kuber/pre/apimachinery_version.py
kuber/pre/apiregistration_v1.py
kuber/pre/apiserverinternal_v1alpha1.py
kuber-1.19.0.dist-info/LICENSE
kuber-1.19.0.dist-info/METADATA
kuber-1.19.0.dist-info/WHEEL
kuber-1.19.0.dist-info/RECORD
