Metadata-Version: 2.3
Name: kuber
Version: 1.19.0
Summary: Accelerated Kubernetes configuration and package management with Python.
License: MIT
Keywords: kubernetes
Author: Scott Ernst
Author-email: swernst@gmail.com
Requires-Python: >=3.11,<3.14
Classifier: Development Status :: 4 - Beta
Classifier: Environment :: Console
Classifier: Intended Audience :: Developers
Classifier: Intended Audience :: System Administrators
Classifier: License :: OSI Approved :: MIT License
Classifier: Programming Language :: Python :: 3
Classifier: Programming Language :: Python :: 3.11
Classifier: Programming Language :: Python :: 3.12
Classifier: Programming Language :: Python :: 3.13
Classifier: Topic :: Software Development :: Libraries
Classifier: Topic :: System :: Systems Administration
Classifier: Topic :: Utilities
Classifier: Typing :: Typed
Requires-Dist: PyYAML (>=6.0.0)
Requires-Dist: kubernetes (>=10.0.0)
Requires-Dist: requests (>=2.20.0)
Requires-Dist: semver (>=2.9.0)
Project-URL: Documentation, https://kuber.readthedocs.io/en/latest/
Project-URL: Homepage, https://github.com/sernst/kuber
Project-URL: Repository, https://github.com/sernst/kuber
